RegisterFile/MiniRegisterFile.v
module MiniRegisterFile(BusA, BusB, BusW, RA, RB, RW, RegWr, Clk);
    output [63:0] BusA;
    output [63:0] BusB;
    input [63:0] BusW;
    input [4:0] RA;
    input [4:0] RB;
    input [4:0] RW;
    input RegWr;
    input Clk;
    reg [63:0] registers [31:0];
     
    always @(posedge Clk or negedge Clk) begin
        registers[31] <= 64'b0;
    end
    assign #2 BusA = registers[RA];
    assign #2 BusB = registers[RB];
     
    always @ (negedge Clk) begin
        if(RegWr && RW != 31)
            registers[RW] <= #3 BusW;
    end
endmodule

RegisterFile/RegisterFileTest_custom.v
`timescale 1ns / 1ps

`define STRLEN 32
module RegisterFileTest_v;
initial begin
        $dumpfile("RegisterFileTest.vcd");
        $dumpvars(0, RegisterFileTest_v);
    end

	task passTest;
		input [63:0] actualOut, expectedOut;
		input [`STRLEN*8:0] testType;
		inout [7:0] passed;
	
		if(actualOut == expectedOut) begin $display ("%s passed", testType); passed = passed + 1; end
		else $display ("%s failed: %d should be %d", testType, actualOut, expectedOut);
	endtask
	
	task allPassed;
		input [7:0] passed;
		input [7:0] numTests;
		
		if(passed == numTests) $display ("All tests passed");
		else $display("Some tests failed");
	endtask

	// Inputs
	reg [63:0] BusW;
	reg [4:0] RA;
	reg [4:0] RB;
	reg [4:0] RW;
	reg RegWr;
	reg Clk;
	reg [7:0] passed;

	// Outputs
	wire [63:0] BusA;
	wire [63:0] BusB;

	// Instantiate the Unit Under Test (UUT)
	MiniRegisterFile uut (
		.BusA(BusA), 
		.BusB(BusB), 
		.BusW(BusW), 
		.RA(RA), 
		.RB(RB), 
		.RW(RW), 
		.RegWr(RegWr), 
		.Clk(Clk)
	);

    integer i;
    initial begin
		Clk = 0;
		passed = 0;
        $display("Initializing registers to their respective numbers...");
        for(i=0;i<32;i=i+1)begin
            RW = i;
            if(i!=31)begin 
                BusW = i;
            end
            else begin 
                BusW = 0;
            end
            RegWr = 1;
            #5 Clk = 1; #5 Clk = 0;
        end
        RegWr = 0;

        {RA, RB, RW, BusW, RegWr} = {5'h0, 5'h1, 5'h0, 64'h0, 1'b0};
		#10
		passTest(BusA, 64'd0, "Initial value check 1", passed);
		passTest(BusB, 64'd1, "Initial value check 2", passed);
		#10; Clk = 0; #10; Clk = 1;

        {RA, RB, RW, BusW, RegWr} = {5'h2, 5'h3, 5'h1, 64'h1000, 1'b0};
		#10
		passTest(BusA, 64'd2, "Initial value check 3", passed);
		passTest(BusB, 64'd3, "Initial value check 4", passed);
		#10; Clk = 0; #10; Clk = 1;
        
        {RA, RB, RW, BusW, RegWr} = {5'h4, 5'h5, 5'h0, 64'h1000, 1'b1};
		#10
		passTest(BusA, 64'd4, "Initial value check 5", passed);
		passTest(BusB, 64'd5, "Initial value check 6", passed);
		#10; Clk = 0; #10; Clk = 1;

        {RA, RB, RW, BusW, RegWr} = {5'h6, 5'h7, 5'hA, 64'h1010, 1'b1};
		#10
		passTest(BusA, 64'd6, "Initial value check 7", passed);
		passTest(BusB, 64'd7, "Initial value check 8", passed);
		#10; Clk = 0; #10; Clk = 1;

        {RA, RB, RW, BusW, RegWr} = {5'h8, 5'h9, 5'hB, 64'h103000, 1'b1};
		#10
		passTest(BusA, 64'd8, "Initial value check 9", passed);
		passTest(BusB, 64'd9, "Initial value check 10", passed);
		#10; Clk = 0; #10; Clk = 1;

        {RA, RB, RW, BusW, RegWr} = {5'hA, 5'hB, 5'hC, 64'h0, 1'b0};
		#10
		passTest(BusA, 64'd4112, "Initial value check 11", passed);
		passTest(BusB, 64'd1060864, "Initial value check 12", passed);
		#10; Clk = 0; #10; Clk = 1;

        {RA, RB, RW, BusW, RegWr} = {5'hC, 5'hD, 5'hD, 64'hABCD, 1'b1};
		#10
		passTest(BusA, 64'd12, "Initial value check 13", passed);
		passTest(BusB, 64'd43981, "Initial value check 14", passed);
		#10; Clk = 0; #10; Clk = 1;

        {RA, RB, RW, BusW, RegWr} = {5'hE, 5'hF, 5'hE, 64'h9080009, 1'b0};
		#10
		passTest(BusA, 64'd14, "Initial value check 15", passed);
		passTest(BusB, 64'd15, "Initial value check 16", passed);
		#10; Clk = 0; #10; Clk = 1;

        allPassed(passed, 16);
        $finish;
    end
    always #5 Clk = ~Clk;
endmodule

RegisterFile/RegisterFileTest.vcd
$date
	Thu Nov 14 01:00:47 2024
$end
$version
	Icarus Verilog
$end
$timescale
	1ps
$end
$scope module RegisterFileTest_v $end
$var wire 64 ! BusB [63:0] $end
$var wire 64 " BusA [63:0] $end
$var reg 64 # BusW [63:0] $end
$var reg 1 $ Clk $end
$var reg 5 % RA [4:0] $end
$var reg 5 & RB [4:0] $end
$var reg 5 ' RW [4:0] $end
$var reg 1 ( RegWr $end
$var reg 8 ) passed [7:0] $end
$var integer 32 * i [31:0] $end
$scope module uut $end
$var wire 64 + BusA [63:0] $end
$var wire 64 , BusB [63:0] $end
$var wire 64 - BusW [63:0] $end
$var wire 1 $ Clk $end
$var wire 5 . RA [4:0] $end
$var wire 5 / RB [4:0] $end
$var wire 5 0 RW [4:0] $end
$var wire 1 ( RegWr $end
$upscope $end
$scope task allPassed $end
$var reg 8 1 numTests [7:0] $end
$var reg 8 2 passed [7:0] $end
$upscope $end
$scope task passTest $end
$var reg 64 3 actualOut [63:0] $end
$var reg 64 4 expectedOut [63:0] $end
$var reg 8 5 passed [7:0] $end
$var reg 257 6 testType [256:0] $end
$upscope $end
$upscope $end
$enddefinitions $end
$comment Show the parameter values. $end
$dumpall
$end
#0
$dumpvars
bx 6
bx 5
bx 4
bx 3
bx 2
bx 1
b0 0
bx /
bx .
b0 -
bx ,
bx +
b0 *
b0 )
1(
b0 '
bx &
bx %
0$
b0 #
bx "
bx !
$end
#5000
0$
#10000
1$
b1 #
b1 -
b1 '
b1 0
b1 *
#15000
0$
#20000
1$
b10 #
b10 -
b10 '
b10 0
b10 *
#25000
0$
#30000
1$
b11 #
b11 -
b11 '
b11 0
b11 *
#35000
0$
#40000
1$
b100 #
b100 -
b100 '
b100 0
b100 *
#45000
0$
#50000
1$
b101 #
b101 -
b101 '
b101 0
b101 *
#55000
0$
#60000
1$
b110 #
b110 -
b110 '
b110 0
b110 *
#65000
0$
#70000
1$
b111 #
b111 -
b111 '
b111 0
b111 *
#75000
0$
#80000
1$
b1000 #
b1000 -
b1000 '
b1000 0
b1000 *
#85000
0$
#90000
1$
b1001 #
b1001 -
b1001 '
b1001 0
b1001 *
#95000
0$
#100000
1$
b1010 #
b1010 -
b1010 '
b1010 0
b1010 *
#105000
0$
#110000
1$
b1011 #
b1011 -
b1011 '
b1011 0
b1011 *
#115000
0$
#120000
1$
b1100 #
b1100 -
b1100 '
b1100 0
b1100 *
#125000
0$
#130000
1$
b1101 #
b1101 -
b1101 '
b1101 0
b1101 *
#135000
0$
#140000
1$
b1110 #
b1110 -
b1110 '
b1110 0
b1110 *
#145000
0$
#150000
1$
b1111 #
b1111 -
b1111 '
b1111 0
b1111 *
#155000
0$
#160000
1$
b10000 #
b10000 -
b10000 '
b10000 0
b10000 *
#165000
0$
#170000
1$
b10001 #
b10001 -
b10001 '
b10001 0
b10001 *
#175000
0$
#180000
1$
b10010 #
b10010 -
b10010 '
b10010 0
b10010 *
#185000
0$
#190000
1$
b10011 #
b10011 -
b10011 '
b10011 0
b10011 *
#195000
0$
#200000
1$
b10100 #
b10100 -
b10100 '
b10100 0
b10100 *
#205000
0$
#210000
1$
b10101 #
b10101 -
b10101 '
b10101 0
b10101 *
#215000
0$
#220000
1$
b10110 #
b10110 -
b10110 '
b10110 0
b10110 *
#225000
0$
#230000
1$
b10111 #
b10111 -
b10111 '
b10111 0
b10111 *
#235000
0$
#240000
1$
b11000 #
b11000 -
b11000 '
b11000 0
b11000 *
#245000
0$
#250000
1$
b11001 #
b11001 -
b11001 '
b11001 0
b11001 *
#255000
0$
#260000
1$
b11010 #
b11010 -
b11010 '
b11010 0
b11010 *
#265000
0$
#270000
1$
b11011 #
b11011 -
b11011 '
b11011 0
b11011 *
#275000
0$
#280000
1$
b11100 #
b11100 -
b11100 '
b11100 0
b11100 *
#285000
0$
#290000
1$
b11101 #
b11101 -
b11101 '
b11101 0
b11101 *
#295000
0$
#300000
1$
b11110 #
b11110 -
b11110 '
b11110 0
b11110 *
#305000
0$
#310000
1$
b0 #
b0 -
b11111 '
b11111 0
b11111 *
#315000
0$
#320000
1$
b0 %
b0 .
b1 &
b1 /
b0 '
b0 0
0(
b100000 *
#322000
b0 "
b0 +
b1 !
b1 ,
#325000
0$
#330000
1$
b10 )
b10 5
b10010010110111001101001011101000110100101100001011011000010000001110110011000010110110001110101011001010010000001100011011010000110010101100011011010110010000000110010 6
b1 4
b1 3
#335000
0$
#340000
1$
#345000
0$
#350000
b10 %
b10 .
b11 &
b11 /
b1 '
b1 0
b1000000000000 #
b1000000000000 -
0$
#352000
b10 "
b10 +
b11 !
b11 ,
#355000
1$
#360000
0$
b100 )
b100 5
b10010010110111001101001011101000110100101100001011011000010000001110110011000010110110001110101011001010010000001100011011010000110010101100011011010110010000000110100 6
b11 4
b11 3
#365000
1$
#370000
1$
#375000
0$
#380000
b100 %
b100 .
b101 &
b101 /
b0 '
b0 0
1(
0$
#382000
b100 "
b100 +
b101 !
b101 ,
#385000
1$
#390000
0$
b110 )
b110 5
b10010010110111001101001011101000110100101100001011011000010000001110110011000010110110001110101011001010010000001100011011010000110010101100011011010110010000000110110 6
b101 4
b101 3
#395000
1$
#400000
1$
#405000
0$
#410000
b110 %
b110 .
b111 &
b111 /
b1010 '
b1010 0
b1000000010000 #
b1000000010000 -
0$
#412000
b110 "
b110 +
b111 !
b111 ,
#415000
1$
#420000
0$
b1000 )
b1000 5
b10010010110111001101001011101000110100101100001011011000010000001110110011000010110110001110101011001010010000001100011011010000110010101100011011010110010000000111000 6
b111 4
b111 3
#425000
1$
#430000
1$
#435000
0$
#440000
b1000 %
b1000 .
b1001 &
b1001 /
b1011 '
b1011 0
b100000011000000000000 #
b100000011000000000000 -
0$
#442000
b1000 "
b1000 +
b1001 !
b1001 ,
#445000
1$
#450000
0$
b1010 )
b1010 5
b1001001011011100110100101110100011010010110000101101100001000000111011001100001011011000111010101100101001000000110001101101000011001010110001101101011001000000011000100110000 6
b1001 4
b1001 3
#455000
1$
#460000
1$
#465000
0$
#470000
b1010 %
b1010 .
b1011 &
b1011 /
b1100 '
b1100 0
b0 #
b0 -
0(
0$
#472000
b1000000010000 "
b1000000010000 +
b100000011000000000000 !
b100000011000000000000 ,
#475000
1$
#480000
0$
b1100 )
b1100 5
b1001001011011100110100101110100011010010110000101101100001000000111011001100001011011000111010101100101001000000110001101101000011001010110001101101011001000000011000100110010 6
b100000011000000000000 4
b100000011000000000000 3
#485000
1$
#490000
1$
#495000
0$
#500000
b1100 %
b1100 .
b1101 &
b1101 /
b1101 '
b1101 0
b1010101111001101 #
b1010101111001101 -
1(
0$
#502000
b1100 "
b1100 +
b1101 !
b1101 ,
#505000
b1010101111001101 !
b1010101111001101 ,
1$
#510000
0$
b1110 )
b1110 5
b1001001011011100110100101110100011010010110000101101100001000000111011001100001011011000111010101100101001000000110001101101000011001010110001101101011001000000011000100110100 6
b1010101111001101 4
b1010101111001101 3
#515000
1$
#520000
1$
#525000
0$
#530000
b1110 %
b1110 .
b1111 &
b1111 /
b1110 '
b1110 0
b1001000010000000000000001001 #
b1001000010000000000000001001 -
0(
0$
#532000
b1110 "
b1110 +
b1111 !
b1111 ,
#535000
1$
#540000
0$
b10000 )
b10000 5
b1001001011011100110100101110100011010010110000101101100001000000111011001100001011011000111010101100101001000000110001101101000011001010110001101101011001000000011000100110110 6
b1111 4
b1111 3
#545000
1$
#550000
1$
#555000
0$
#560000
b10000 1
b10000 2
0$
