NextPClogic/NextPClogic.v
module NextPClogic(NextPC, CurrentPC, SignExtImm64, Branch, ALUZero, Uncondbranch);
	input [63:0] CurrentPC, SignExtImm64;
	input Branch, ALUZero, Uncondbranch;
	output reg [63:0] NextPC;
	always @(*) begin
		#1;
		if((Branch && ALUZero)||(Uncondbranch && !ALUZero)) begin 
			#2;
			NextPC = CurrentPC + (SignExtImm64 << 2);
		end
		else begin
			#1;
			NextPC = CurrentPC + 4;
		end
	end
endmodule

NextPClogic/NextPClogicTest.v
`timescale 1ns / 1ps

module NextPClogicTest;

    // Inputs
    reg [63:0] CurrentPC;
    reg [63:0] SignExtImm64;
    reg Branch;
    reg ALUZero;
    reg Uncondbranch;

    // Outputs
    wire [63:0] NextPC;

    // Instantiate the Unit Under Test (UUT)
    NextPClogic uut (
        .CurrentPC(CurrentPC),
        .SignExtImm64(SignExtImm64),
        .Branch(Branch),
        .ALUZero(ALUZero),
        .Uncondbranch(Uncondbranch),
        .NextPC(NextPC)
    );

    initial begin
        // Initialize Inputs
        CurrentPC = 0;
        SignExtImm64 = 0;
        Branch = 0;
        ALUZero = 0;
        Uncondbranch = 0;
        #10;

        // Test Case 1: Default next instruction
        CurrentPC = 64'h1000;
        SignExtImm64 = 64'h0;
        Branch = 0;
        ALUZero = 0;
        Uncondbranch = 0;
        #5; // Wait for delay to ensure processing
        $display("CurrentPC: %h, SignExtImm64: %h, Branch: %h, ALUZero: %h, Uncondbranch: %h, NextPC: %h", CurrentPC, SignExtImm64, Branch, ALUZero, Uncondbranch, NextPC);
        if (NextPC !== 64'h1004) $display("Test Case 1 Failed: NextPC = %h", NextPC);
        else $display("Test Case 1 Passed: NextPC = %h", NextPC);
        
        // Test Case 2: Conditional branch taken
        CurrentPC = 64'h1000;
        SignExtImm64 = 64'h2;
        Branch = 1;
        ALUZero = 1;
        Uncondbranch = 0;
        #5; // Wait for delay to ensure processing
        $display("CurrentPC: %h, SignExtImm64: %h, Branch: %h, ALUZero: %h, Uncondbranch: %h, NextPC: %h", CurrentPC, SignExtImm64, Branch, ALUZero, Uncondbranch, NextPC);
        if (NextPC !== 64'h1008) $display("Test Case 2 Failed: NextPC = %h", NextPC);
        else $display("Test Case 2 Passed: NextPC = %h", NextPC);

        // Test Case 3: Unconditional branch
        CurrentPC = 64'h1000;
        SignExtImm64 = 64'h1;
        Branch = 0;
        ALUZero = 0;
        Uncondbranch = 1;
        #5; // Wait for delay to ensure processing
        $display("CurrentPC: %h, SignExtImm64: %h, Branch: %h, ALUZero: %h, Uncondbranch: %h, NextPC: %h", CurrentPC, SignExtImm64, Branch, ALUZero, Uncondbranch, NextPC);
        if (NextPC !== 64'h1004) $display("Test Case 3 Failed: NextPC = %h", NextPC);
        else $display("Test Case 3 Passed: NextPC = %h", NextPC);
        
        // Test Case 4: Conditional branch not taken
        CurrentPC = 64'h1000;
        SignExtImm64 = 64'h2;
        Branch = 1;
        ALUZero = 0;
        Uncondbranch = 0;
        #5; // Wait for delay to ensure processing
        $display("CurrentPC: %h, SignExtImm64: %h, Branch: %h, ALUZero: %h, Uncondbranch: %h, NextPC: %h", CurrentPC, SignExtImm64, Branch, ALUZero, Uncondbranch, NextPC);
        if (NextPC !== 64'h1004) $display("Test Case 4 Failed: NextPC = %h", NextPC);
        else $display("Test Case 4 Passed: NextPC = %h", NextPC);

        $display("All test cases passed!");
    end
    initial begin
        $dumpfile("NextPClogicTest.vcd");
        $dumpvars(0, NextPClogicTest);
    end
endmodule

NextPClogic/NextPClogicTest.vcd
$date
	Wed Nov 13 20:19:14 2024
$end
$version
	Icarus Verilog
$end
$timescale
	1ps
$end
$scope module NextPClogicTest $end
$var wire 64 ! NextPC [63:0] $end
$var reg 1 " ALUZero $end
$var reg 1 # Branch $end
$var reg 64 $ CurrentPC [63:0] $end
$var reg 64 % SignExtImm64 [63:0] $end
$var reg 1 & Uncondbranch $end
$scope module uut $end
$var wire 1 " ALUZero $end
$var wire 1 # Branch $end
$var wire 64 ' CurrentPC [63:0] $end
$var wire 64 ( SignExtImm64 [63:0] $end
$var wire 1 & Uncondbranch $end
$var reg 64 ) NextPC [63:0] $end
$upscope $end
$upscope $end
$enddefinitions $end
$comment Show the parameter values. $end
$dumpall
$end
#0
$dumpvars
bx )
b0 (
b0 '
0&
b0 %
b0 $
0#
0"
bx !
$end
#2000
b100 !
b100 )
#10000
b1000000000000 $
b1000000000000 '
#12000
b1000000000100 !
b1000000000100 )
#15000
1"
1#
b10 %
b10 (
#18000
b1000000001000 !
b1000000001000 )
#20000
1&
0"
0#
b1 %
b1 (
#23000
b1000000000100 !
b1000000000100 )
#25000
0&
1#
b10 %
b10 (
