ALU/ALU.v
`define AND   4'b0000
`define OR    4'b0001
`define ADD   4'b0010
`define SUB   4'b0110
`define PassB 4'b0111


module ALU(BusW, BusA, BusB, ALUCtrl, Zero);
    
    parameter n = 64;

    output  [n-1:0] BusW;
    input   [n-1:0] BusA, BusB;
    input   [3:0] ALUCtrl;
    output  Zero;
    
    reg     [n-1:0] BusW;
    
    always @(ALUCtrl or BusA or BusB) begin
        case(ALUCtrl)
            `AND: begin
                BusW = BusA & BusB;
            end
            `OR: begin 
                BusW = BusA | BusB;
            end
            `ADD: begin
                BusW = BusA + BusB;
            end
            `SUB: begin
                BusW = BusA - BusB;
            end
            `PassB: begin 
                BusW = BusB;
            end
        endcase
    end

    assign #1 Zero = !BusW;
endmodule

ALU/ALUTest.v
`timescale 1ns / 1ps

////////////////////////////////////////////////////////////////////////////////
// Company: 
// Engineer:
//
// Create Date:   10:02:47 03/05/2009
// Design Name:   ALU
// Module Name:   E:/350/Lab8/ALU/ALUTest.v
// Project Name:  ALU
// Target Device:  
// Tool versions:  
// Description: 
//
// Verilog Test Fixture created by ISE for module: ALU
//
// Dependencies:
// 
// Revision:
// Revision 0.01 - File Created
// Additional Comments:
// 
////////////////////////////////////////////////////////////////////////////////

`define STRLEN 32
module ALUTest_v;

	task passTest;
		input [64:0] actualOut, expectedOut;
		input [`STRLEN*8:0] testType;
		inout [7:0] passed;
	
		if(actualOut == expectedOut) begin $display ("%s passed", testType); passed = passed + 1; end
		else $display ("%s failed: %x should be %x", testType, actualOut, expectedOut);
	endtask
	
	task allPassed;
		input [7:0] passed;
		input [7:0] numTests;
		
		if(passed == numTests) $display ("All tests passed");
		else $display("Some tests failed");
	endtask

	// Inputs
	reg [63:0] BusA;
	reg [63:0] BusB;
	reg [3:0] ALUCtrl;
	reg [7:0] passed;

	// Outputs
	wire [63:0] BusW;
	wire Zero;

	// Instantiate the Unit Under Test (UUT)
	ALU uut (
		.BusW(BusW), 
		.Zero(Zero), 
		.BusA(BusA), 
		.BusB(BusB), 
		.ALUCtrl(ALUCtrl)
	);

	initial begin
		// Initialize Inputs
		BusA = 0;
		BusB = 0;
		ALUCtrl = 0;
		passed = 0;

        // Here is one example test vector, testing the ADD instruction:
		// {BusA, BusB, ALUCtrl} = {64'h1234, 64'hABCD0000, 4'h2}; #40; passTest({Zero, BusW}, 65'h0ABCD1234, "ADD 0x1234,0xABCD0000", passed);
		//Reformate and add your test vectors from the prelab here following the example of the testvector above.	
		{BusA, BusB, ALUCtrl} = {64'h8, 64'h8, 4'h0}; #40; passTest({Zero, BusW}, {1'h0,64'h8}, "AND 0x8,0x8", passed);
		{BusA, BusB, ALUCtrl} = {64'h5, 64'h7, 4'h0}; #40; passTest({Zero, BusW}, {1'h0,64'h5}, "AND 0x5,0x7", passed);
		{BusA, BusB, ALUCtrl} = {64'h8, 64'h0, 4'h0}; #40; passTest({Zero, BusW}, {1'h1,64'h0}, "AND 0x8,0x0", passed);
		{BusA, BusB, ALUCtrl} = {64'h0, 64'h0, 4'h1}; #40; passTest({Zero, BusW}, {1'h1,64'h0}, "OR 0x0,0x0", passed);
		{BusA, BusB, ALUCtrl} = {64'h7, 64'h0, 4'h1}; #40; passTest({Zero, BusW}, {1'h0,64'h7}, "OR 0x7,0x0", passed);
		{BusA, BusB, ALUCtrl} = {64'h7, 64'h5, 4'h1}; #40; passTest({Zero, BusW}, {1'h0,64'h7}, "OR 0x7,0x5", passed);
		{BusA, BusB, ALUCtrl} = {64'h0, 64'h0, 4'h2}; #40; passTest({Zero, BusW}, {1'h1,64'h0}, "ADD 0x0,0x0", passed);
		{BusA, BusB, ALUCtrl} = {64'h5, 64'h5, 4'h2}; #40; passTest({Zero, BusW}, {1'h0,64'hA}, "ADD 0x5,0x5", passed);
		{BusA, BusB, ALUCtrl} = {64'h7, 64'h3, 4'h2}; #40; passTest({Zero, BusW}, {1'h0,64'hA}, "ADD 0x7,0x3", passed);
		{BusA, BusB, ALUCtrl} = {64'h5, 64'h5, 4'h6}; #40; passTest({Zero, BusW}, {1'h1,64'h0}, "SUB 0x5,0x5", passed);
		{BusA, BusB, ALUCtrl} = {64'h5, 64'h2, 4'h6}; #40; passTest({Zero, BusW}, {1'h0,64'h3}, "SUB 0x5,0x2", passed);
		{BusA, BusB, ALUCtrl} = {64'hB, 64'h8, 4'h6}; #40; passTest({Zero, BusW}, {1'h0,64'h3}, "SUB 0xB,0x8", passed);
		{BusA, BusB, ALUCtrl} = {64'h0, 64'h0, 4'h7}; #40; passTest({Zero, BusW}, {1'h1,64'h0}, "PASS 0x0,0x0", passed);
		{BusA, BusB, ALUCtrl} = {64'hB, 64'hF, 4'h7}; #40; passTest({Zero, BusW}, {1'h0,64'hF}, "PASS 0xB,0xF", passed);
		{BusA, BusB, ALUCtrl} = {64'h8, 64'h6, 4'h7}; #40; passTest({Zero, BusW}, {1'h0,64'h6}, "PASS 0x8,0x6", passed);
		allPassed(passed, 15);
	end
	initial begin
		$dumpfile("ALUTest.vcd");
		$dumpvars(0,ALUTest_v);
	end
      
endmodule

ALU/ALUTest.vcd
$date
	Thu Nov  7 17:32:34 2024
$end
$version
	Icarus Verilog
$end
$timescale
	1ps
$end
$scope module ALUTest_v $end
$var wire 1 ! Zero $end
$var wire 64 " BusW [63:0] $end
$var reg 4 # ALUCtrl [3:0] $end
$var reg 64 $ BusA [63:0] $end
$var reg 64 % BusB [63:0] $end
$var reg 8 & passed [7:0] $end
$scope module uut $end
$var wire 4 ' ALUCtrl [3:0] $end
$var wire 64 ( BusA [63:0] $end
$var wire 64 ) BusB [63:0] $end
$var wire 1 ! Zero $end
$var parameter 32 * n $end
$var reg 64 + BusW [63:0] $end
$upscope $end
$scope task allPassed $end
$var reg 8 , numTests [7:0] $end
$var reg 8 - passed [7:0] $end
$upscope $end
$scope task passTest $end
$var reg 65 . actualOut [64:0] $end
$var reg 65 / expectedOut [64:0] $end
$var reg 8 0 passed [7:0] $end
$var reg 257 1 testType [256:0] $end
$upscope $end
$upscope $end
$enddefinitions $end
$comment Show the parameter values. $end
$dumpall
b1000000 *
$end
#0
$dumpvars
bx 1
bx 0
bx /
bx .
bx -
bx ,
b1000 +
b1000 )
b1000 (
b0 '
b0 &
b1000 %
b1000 $
b0 #
b1000 "
x!
$end
#1000
0!
#40000
b101 "
b101 +
b101 $
b101 (
b111 %
b111 )
b1 &
b1 0
b100000101001110010001000010000000110000011110000011100000101100001100000111100000111000 1
b1000 /
b1000 .
#80000
b0 "
b0 +
b1000 $
b1000 (
b0 %
b0 )
b10 &
b10 0
b100000101001110010001000010000000110000011110000011010100101100001100000111100000110111 1
b101 /
b101 .
#81000
1!
#120000
b0 $
b0 (
b1 #
b1 '
b11 &
b11 0
b100000101001110010001000010000000110000011110000011100000101100001100000111100000110000 1
b10000000000000000000000000000000000000000000000000000000000000000 /
b10000000000000000000000000000000000000000000000000000000000000000 .
#160000
b111 "
b111 +
b111 $
b111 (
b100 &
b100 0
b1001111010100100010000000110000011110000011000000101100001100000111100000110000 1
#161000
0!
#200000
b101 %
b101 )
b101 &
b101 0
b1001111010100100010000000110000011110000011011100101100001100000111100000110000 1
b111 /
b111 .
#240000
b0 "
b0 +
b0 $
b0 (
b0 %
b0 )
b10 #
b10 '
b110 &
b110 0
b1001111010100100010000000110000011110000011011100101100001100000111100000110101 1
#241000
1!
#280000
b1010 "
b1010 +
b101 $
b101 (
b101 %
b101 )
b111 &
b111 0
b100000101000100010001000010000000110000011110000011000000101100001100000111100000110000 1
b10000000000000000000000000000000000000000000000000000000000000000 /
b10000000000000000000000000000000000000000000000000000000000000000 .
#281000
0!
#320000
b111 $
b111 (
b11 %
b11 )
b1000 &
b1000 0
b100000101000100010001000010000000110000011110000011010100101100001100000111100000110101 1
b1010 /
b1010 .
#360000
b0 "
b0 +
b101 $
b101 (
b101 %
b101 )
b110 #
b110 '
b1001 &
b1001 0
b100000101000100010001000010000000110000011110000011011100101100001100000111100000110011 1
#361000
1!
#400000
b11 "
b11 +
b10 %
b10 )
b1010 &
b1010 0
b101001101010101010000100010000000110000011110000011010100101100001100000111100000110101 1
b10000000000000000000000000000000000000000000000000000000000000000 /
b10000000000000000000000000000000000000000000000000000000000000000 .
#401000
0!
#440000
b1011 $
b1011 (
b1000 %
b1000 )
b1011 &
b1011 0
b101001101010101010000100010000000110000011110000011010100101100001100000111100000110010 1
b11 /
b11 .
#480000
b0 "
b0 +
b0 $
b0 (
b0 %
b0 )
b111 #
b111 '
b1100 &
b1100 0
b101001101010101010000100010000000110000011110000100001000101100001100000111100000111000 1
#481000
1!
#520000
b1111 "
b1111 +
b1011 $
b1011 (
b1111 %
b1111 )
b1101 &
b1101 0
b10100000100000101010011010100110010000000110000011110000011000000101100001100000111100000110000 1
b10000000000000000000000000000000000000000000000000000000000000000 /
b10000000000000000000000000000000000000000000000000000000000000000 .
#521000
0!
#560000
b110 "
b110 +
b1000 $
b1000 (
b110 %
b110 )
b1110 &
b1110 0
b10100000100000101010011010100110010000000110000011110000100001000101100001100000111100001000110 1
b1111 /
b1111 .
#600000
b1111 ,
b1111 -
b1111 &
b1111 0
b10100000100000101010011010100110010000000110000011110000011100000101100001100000111100000110110 1
b110 /
b110 .
